iflow_mcp_run_llama_mcp_on_cloudrun/__init__.py
iflow_mcp_run_llama_mcp_on_cloudrun/config.py
iflow_mcp_run_llama_mcp_on_cloudrun/models.py
iflow_mcp_run_llama_mcp_on_cloudrun/run_server.py
iflow_mcp_run_llama_mcp_on_cloudrun/server.py
iflow_mcp_run_llama_mcp_on_cloudrun/services/__init__.py
iflow_mcp_run_llama_mcp_on_cloudrun/services/llamacloud_service.py
iflow_mcp_run_llama_mcp_on_cloudrun/services/openai_service.py
iflow_mcp_run_llama_mcp_on_cloudrun/tools/__init__.py
iflow_mcp_run_llama_mcp_on_cloudrun/tools/candidate_tools.py
iflow_mcp_run_llama_mcp_on_cloudrun/tools/job_tools.py
iflow_mcp_run_llama_mcp_on_cloudrun/tools/math_tools.py
iflow_mcp_run_llama_mcp_on_cloudrun-0.1.6.dist-info/licenses/LICENSE
iflow_mcp_run_llama_mcp_on_cloudrun-0.1.6.dist-info/METADATA
iflow_mcp_run_llama_mcp_on_cloudrun-0.1.6.dist-info/WHEEL
iflow_mcp_run_llama_mcp_on_cloudrun-0.1.6.dist-info/entry_points.txt
iflow_mcp_run_llama_mcp_on_cloudrun-0.1.6.dist-info/top_level.txt
iflow_mcp_run_llama_mcp_on_cloudrun-0.1.6.dist-info/RECORD
