Metadata-Version: 2.4
Name: iflow-mcp_run-llama-mcp-on-cloudrun
Version: 0.1.6
Summary: Example of deploying a MCP server on Cloud Run
Requires-Python: >=3.10
License-File: LICENSE
Requires-Dist: fastmcp==2.4.0
Requires-Dist: httpx>=0.27.0
Requires-Dist: llama-cloud>=0.1.26
Requires-Dist: llama-index>=0.12.43
Requires-Dist: pydantic==2.9.2
Dynamic: license-file
